{
  "slug": "how-to-create-folders-in-microsoft-loop-easily-2026",
  "seoTitle": "How to Create Folders in Microsoft Loop (2026)",
  "metaDescription": "Organize a cluttered Microsoft Loop workspace by using subpages as digital folders, nesting related pages and dragging files between them.",
  "intro": "Microsoft Loop doesn't have traditional folders, but subpages work the same way — letting you group related content into nested, collapsible sections. This guide shows how to build a folder-style structure using subpages and move existing pages into it.",
  "steps": [
    { "heading": "Open your workspace directory", "body": "Open your Microsoft Loop app and select the working directory you want to organize." },
    { "heading": "Find the parent page", "body": "Go to the left sidebar content tree and locate the specific document you want to organize under." },
    { "heading": "Open the subpage options", "body": "Hover over the title, click the three dots icon, and select 'Add New Subpage' from the dropdown list." },
    { "heading": "Name your folder", "body": "Enter a descriptive folder name and press Enter to lock in the new subpage boundary." },
    { "heading": "Move existing pages into it", "body": "Click and hold external page nodes in the sidebar and drag them into your new subfolder to organize related content." }
  ],
  "faq": [
    { "question": "Does Microsoft Loop have a dedicated folder feature?", "answer": "Not exactly — subpages act as the folder equivalent, letting you nest related pages under a parent page in the sidebar." },
    { "question": "Can I nest folders multiple levels deep?", "answer": "Yes, you can create multiple layers of sub-nodes to group distinct content types as deeply as your project needs." },
    { "question": "Can I collapse folders in the sidebar to reduce clutter?", "answer": "Yes, expanding and collapsing multi-tiered workspace layouts helps keep the active page list scannable." },
    { "question": "What happens to a page's content when I move it into a subfolder?", "answer": "Dragging a page into a subpage location reorganizes its place in the sidebar tree without altering its content." }
  ],
  "generatedAt": "2026-07-22T00:00:00.000Z"
}
