{
  "slug": "how-to-create-an-instagram-reel-in-canva-easily-2026",
  "seoTitle": "How to Create an Instagram Reel in Canva",
  "metaDescription": "Learn how to build an engaging Instagram Reel using Canva's templates, animations, and editing tools, then export it ready to post.",
  "intro": "Short-form video content like Instagram Reels tends to grab more attention than static posts, and Canva makes creating them approachable for beginners. This tutorial covers setting up your account, choosing a template, and editing your Reel before exporting it.",
  "steps": [
    { "heading": "Set up your Canva account for Reels", "body": "Make sure your account is ready to start building video content inside Canva." },
    { "heading": "Navigate the Canva interface for Reels", "body": "Find where Reel templates and video editing tools are located." },
    { "heading": "Choose the right template", "body": "Pick a template that fits the tone and message of your Reel." },
    { "heading": "Edit your Reel with text and animations", "body": "Add text, animations, and music to make your Reel more engaging." },
    { "heading": "Export and upload to Instagram", "body": "Finalize your Reel and export it in the right format for uploading to Instagram." }
  ],
  "faq": [
    { "question": "Do I need video editing experience to make a Reel in Canva?", "answer": "No, Canva's intuitive interface is built to make Reel creation accessible even for complete beginners." },
    { "question": "Can I create multiple Reels quickly using templates?", "answer": "Yes, you can reuse templates and existing content to produce multiple Reels efficiently." },
    { "question": "What can Reels be used for in a business context?", "answer": "Businesses can use Reels to showcase products, share customer testimonials, or highlight promotions." },
    { "question": "How do I get the Reel onto Instagram after editing?", "answer": "Once your Reel is finished in Canva, you export it and then upload it directly to Instagram." }
  ],
  "generatedAt": "2026-07-21T00:00:00Z"
}
