{
  "slug": "how-to-run-an-income-statement-in-quickbooks-online-easily-2026",
  "seoTitle": "How to Run an Income Statement in QuickBooks Online",
  "metaDescription": "Generate and customize an income statement in QuickBooks Online to review revenue, expenses, and profitability quickly.",
  "intro": "An income statement gives you a clear snapshot of revenue, expenses, and profit over a period, which makes it one of the most useful reports for understanding how your business is actually performing. This guide covers finding the report, customizing it, and reading the results in QuickBooks Online. It's aimed at small business owners and finance professionals reviewing performance regularly.",
  "steps": [
    {
      "heading": "Access QuickBooks Online reports",
      "body": "Navigate to the reports section where the Income Statement (Profit and Loss) is located."
    },
    {
      "heading": "Customize your income statement",
      "body": "Adjust the date range and filters so the report reflects the period you want to analyze."
    },
    {
      "heading": "Analyze your report",
      "body": "Review revenue, expenses, and profit figures to understand your business's financial performance."
    },
    {
      "heading": "Apply best practices",
      "body": "Use the insights from the report to inform budgeting or strategic decisions going forward."
    }
  ],
  "faq": [
    {
      "question": "What's another name for the income statement in QuickBooks?",
      "answer": "It's often labeled the Profit and Loss report within QuickBooks Online."
    },
    {
      "question": "Can I compare income statements across different periods?",
      "answer": "Yes, adjusting the date range settings lets you compare performance across months, quarters, or years."
    },
    {
      "question": "How often should I review my income statement?",
      "answer": "Many businesses review it monthly or quarterly, though frequency depends on your specific needs."
    }
  ],
  "generatedAt": "2026-07-21T00:00:00.000Z"
}
